myst_parser/__init__.py
myst_parser/_compat.py
myst_parser/_docs.py
myst_parser/cli.py
myst_parser/docutils_.py
myst_parser/inventory.py
myst_parser/mocking.py
myst_parser/py.typed
myst_parser/sphinx_.py
myst_parser/warnings_.py
myst_parser/config/__init__.py
myst_parser/config/dc_validators.py
myst_parser/config/main.py
myst_parser/mdit_to_docutils/__init__.py
myst_parser/mdit_to_docutils/base.py
myst_parser/mdit_to_docutils/html_to_nodes.py
myst_parser/mdit_to_docutils/sphinx_.py
myst_parser/mdit_to_docutils/transforms.py
myst_parser/parsers/__init__.py
myst_parser/parsers/directives.py
myst_parser/parsers/docutils_.py
myst_parser/parsers/mdit.py
myst_parser/parsers/options.py
myst_parser/parsers/parse_html.py
myst_parser/parsers/sphinx_.py
myst_parser/sphinx_ext/__init__.py
myst_parser/sphinx_ext/directives.py
myst_parser/sphinx_ext/main.py
myst_parser/sphinx_ext/mathjax.py
myst_parser/sphinx_ext/myst_refs.py
myst_docutils-5.0.0.dist-info/entry_points.txt
myst_docutils-5.0.0.dist-info/licenses/LICENSE
myst_docutils-5.0.0.dist-info/WHEEL
myst_docutils-5.0.0.dist-info/METADATA
myst_docutils-5.0.0.dist-info/RECORD
