Metadata-Version: 2.4
Name: myst-docutils
Version: 5.0.0
Summary: An extended [CommonMark](https://spec.commonmark.org/) compliant parser,
Keywords: markdown,lexer,parser,development,docutils,sphinx
Author-email: Chris Sewell <chrisj_sewell@hotmail.com>
Requires-Python: >=3.11
Classifier: Development Status :: 4 - Beta
Classifier: Framework :: Sphinx :: Extension
Classifier: Intended Audience :: Developers
Classifier: License :: OSI Approved :: MIT License
Classifier: Programming Language :: Python :: 3
Classifier: Programming Language :: Python :: 3 :: Only
Classifier: Programming Language :: Python :: 3.11
Classifier: Programming Language :: Python :: 3.12
Classifier: Programming Language :: Python :: 3.13
Classifier: Programming Language :: Python :: 3.14
Classifier: Programming Language :: Python :: Implementation :: CPython
Classifier: Programming Language :: Python :: Implementation :: PyPy
Classifier: Topic :: Software Development :: Libraries :: Python Modules
Classifier: Topic :: Text Processing :: Markup
License-File: LICENSE
Requires-Dist: jinja2
Requires-Dist: markdown-it-py~=4.0
Requires-Dist: mdit-py-plugins~=0.5
Requires-Dist: pyyaml
Requires-Dist: pre-commit~=4.0 ; extra == "code-style"
Requires-Dist: linkify-it-py~=2.0 ; extra == "linkify"
Requires-Dist: sphinx>=8 ; extra == "rtd"
Requires-Dist: ipython ; extra == "rtd"
Requires-Dist: sphinx-book-theme~=1.1 ; extra == "rtd"
Requires-Dist: sphinx-design ; extra == "rtd"
Requires-Dist: sphinx-copybutton ; extra == "rtd"
Requires-Dist: sphinxext-rediraffe~=0.3.0 ; extra == "rtd"
Requires-Dist: sphinxext-opengraph~=0.13.0 ; extra == "rtd"
Requires-Dist: sphinx-pyscript ; extra == "rtd"
Requires-Dist: sphinx-tippy>=0.4.3 ; extra == "rtd"
Requires-Dist: sphinx-autodoc2~=0.5.0 ; extra == "rtd"
Requires-Dist: sphinx-togglebutton ; extra == "rtd"
Requires-Dist: docutils>=0.20,<0.23 ; extra == "sphinx"
Requires-Dist: sphinx>=8,<10 ; extra == "sphinx"
Requires-Dist: beautifulsoup4 ; extra == "testing"
Requires-Dist: coverage[toml] ; extra == "testing"
Requires-Dist: defusedxml ; extra == "testing"
Requires-Dist: pytest>=9,<10 ; extra == "testing"
Requires-Dist: pytest-cov ; extra == "testing"
Requires-Dist: pytest-regressions ; extra == "testing"
Requires-Dist: pytest-param-files~=0.6.0 ; extra == "testing"
Requires-Dist: sphinx-pytest~=0.3.0 ; extra == "testing"
Requires-Dist: pygments<2.20 ; extra == "testing"
Requires-Dist: pygments ; extra == "testing-docutils"
Requires-Dist: pytest>=9,<10 ; extra == "testing-docutils"
Requires-Dist: pytest-param-files~=0.6.0 ; extra == "testing-docutils"
Project-URL: Documentation, https://myst-parser.readthedocs.io
Project-URL: Homepage, https://github.com/executablebooks/MyST-Parser
Provides-Extra: code-style
Provides-Extra: linkify
Provides-Extra: rtd
Provides-Extra: sphinx
Provides-Extra: testing
Provides-Extra: testing-docutils
